exactextract-0.2.2.dist-info/RECORD
exactextract-0.2.2.dist-info/WHEEL
exactextract-0.2.2.dist-info/METADATA
exactextract-0.2.2.dist-info/licenses/LICENSE
exactextract-0.2.2.dist-info/licenses/LICENSE_GEOS
exactextract/__init__.py
exactextract/processor.py
exactextract/feature.py
exactextract/operation.py
exactextract/writer.py
exactextract/exact_extract.py
exactextract/_exactextract.cpython-313-darwin.so
exactextract/raster.py
exactextract/.dylibs/libgeos_c.1.19.2.dylib
exactextract/.dylibs/libgeos.3.13.1.dylib
