Metadata-Version: 2.2
Name: exactextract
Version: 0.2.2
Summary: Fast and accurate raster zonal statistics
Author: Daniel Baston
License: 
Classifier: Operating System :: Unix
Classifier: Operating System :: MacOS
Classifier: Operating System :: Microsoft :: Windows
Classifier: Programming Language :: Python :: 3
Classifier: Programming Language :: Python :: 3.9
Classifier: Programming Language :: Python :: 3.10
Classifier: Programming Language :: Python :: 3.11
Classifier: Programming Language :: Python :: 3.12
Classifier: Programming Language :: Python :: 3.13
Project-URL: Homepage, https://isciences.github.io/exactextract/
Project-URL: Documentation, https://isciences.github.io/exactextract/
Project-URL: Repository, https://github.com/isciences/exactextract
Project-URL: Issues, https://github.com/isciences/exactextract/issues
Project-URL: Changelog, https://github.com/isciences/exactextract/blob/master/NEWS.md
Requires-Python: >=3.9
Requires-Dist: numpy
